HISTORY.md
LICENSE
MANIFEST.in
README.md
setup.py
tox.ini
docs/Makefile
docs/conf.py
docs/index.rst
docs/requirements.txt
docs/_static/.gitignore
docs/_static/img/example-docx-01.png
docs/_static/img/hdrftr-01.png
docs/_static/img/hdrftr-02.png
docs/_static/img/oss.png
docs/_templates/layout.html
docs/_templates/sidebarlinks.html
docs/_themes/armstrong/LICENSE
docs/_themes/armstrong/layout.html
docs/_themes/armstrong/rtd-themes.conf
docs/_themes/armstrong/theme.conf
docs/_themes/armstrong/theme.conf.orig
docs/_themes/armstrong/static/rtd.css_t
docs/api/dml.rst
docs/api/document.rst
docs/api/section.rst
docs/api/settings.rst
docs/api/shape.rst
docs/api/shared.rst
docs/api/style.rst
docs/api/table.rst
docs/api/text.rst
docs/api/enum/MsoColorType.rst
docs/api/enum/MsoThemeColorIndex.rst
docs/api/enum/WdAlignParagraph.rst
docs/api/enum/WdBuiltinStyle.rst
docs/api/enum/WdCellVerticalAlignment.rst
docs/api/enum/WdColorIndex.rst
docs/api/enum/WdLineSpacing.rst
docs/api/enum/WdOrientation.rst
docs/api/enum/WdRowAlignment.rst
docs/api/enum/WdRowHeightRule.rst
docs/api/enum/WdSectionStart.rst
docs/api/enum/WdStyleType.rst
docs/api/enum/WdTabAlignment.rst
docs/api/enum/WdTabLeader.rst
docs/api/enum/WdTableDirection.rst
docs/api/enum/WdUnderline.rst
docs/api/enum/index.rst
docs/dev/analysis/index.rst
docs/dev/analysis/features/coreprops.rst
docs/dev/analysis/features/header.rst
docs/dev/analysis/features/numbering.rst
docs/dev/analysis/features/sections.rst
docs/dev/analysis/features/settings.rst
docs/dev/analysis/features/shapes/index.rst
docs/dev/analysis/features/shapes/picture.rst
docs/dev/analysis/features/shapes/shapes-inline-size.rst
docs/dev/analysis/features/shapes/shapes-inline.rst
docs/dev/analysis/features/styles/character-style.rst
docs/dev/analysis/features/styles/index.rst
docs/dev/analysis/features/styles/latent-styles.rst
docs/dev/analysis/features/styles/paragraph-style.rst
docs/dev/analysis/features/styles/style.rst
python_docx_oss.egg-info/PKG-INFO
python_docx_oss.egg-info/SOURCES.txt
python_docx_oss.egg-info/dependency_links.txt
python_docx_oss.egg-info/not-zip-safe
python_docx_oss.egg-info/requires.txt
python_docx_oss.egg-info/top_level.txt
