Metadata-Version: 2.4
Name: python-docx-oss
Version: 0.0.10
Summary: CRUD Microsoft Word .docx files.
Home-page: https://github.com/lsaint/python-docx-oss
Author: Ethan St. Lee
Author-email: ethan@ginolegaltech.cn
License: The MIT License (MIT)
Keywords: docx office openxml word python-docx-oss
Classifier: Development Status :: 4 - Beta
Classifier: Environment :: Console
Classifier: Intended Audience :: Developers
Classifier: License :: OSI Approved :: MIT License
Classifier: Operating System :: OS Independent
Classifier: Programming Language :: Python :: 3.10
Classifier: Programming Language :: Python :: 3.11
Classifier: Programming Language :: Python :: 3.12
Classifier: Programming Language :: Python :: 3.13
Classifier: Topic :: Office/Business :: Office Suites
Classifier: Topic :: Software Development :: Libraries
License-File: LICENSE
Requires-Dist: lxml>=4.6.5
Dynamic: author
Dynamic: author-email
Dynamic: classifier
Dynamic: description
Dynamic: description-content-type
Dynamic: home-page
Dynamic: keywords
Dynamic: license
Dynamic: license-file
Dynamic: requires-dist
Dynamic: summary
